tobii_recorder/__init__.py
tobii_recorder/tobii.pyd
tobii_recorder/tobii_interaction_lib.dll
tobii_recorder/tobii_stream_engine.dll
tobii_recorder-0.1.2.dist-info/LICENSE
tobii_recorder-0.1.2.dist-info/METADATA
tobii_recorder-0.1.2.dist-info/WHEEL
tobii_recorder-0.1.2.dist-info/top_level.txt
tobii_recorder-0.1.2.dist-info/RECORD
