Metadata-Version: 2.1
Name: tobii-recorder
Version: 0.1.2
Summary: A Python wrapper for Tobii Eye Tracker data recording
Home-page: https://github.com/mh-salari/tobii_recorder
Author: Mohammadhossein Salari
Author-email: mohammadhossein.salari@gmail.com
Classifier: Programming Language :: Python :: 3
Classifier: License :: Other/Proprietary License
Classifier: Operating System :: Microsoft :: Windows
License-File: LICENSE
